setup.py
ct_dol.egg-info/PKG-INFO
ct_dol.egg-info/SOURCES.txt
ct_dol.egg-info/dependency_links.txt
ct_dol.egg-info/requires.txt
ct_dol.egg-info/top_level.txt
ct_unemployment/__init__.py
ct_unemployment/unemployment.py